tencentcloud/__init__.py
tencentcloud/mongodb/__init__.py
tencentcloud/mongodb/v20180408/__init__.py
tencentcloud/mongodb/v20180408/errorcodes.py
tencentcloud/mongodb/v20180408/models.py
tencentcloud/mongodb/v20180408/mongodb_client.py
tencentcloud/mongodb/v20180408/mongodb_client_async.py
tencentcloud/mongodb/v20190725/__init__.py
tencentcloud/mongodb/v20190725/errorcodes.py
tencentcloud/mongodb/v20190725/models.py
tencentcloud/mongodb/v20190725/mongodb_client.py
tencentcloud/mongodb/v20190725/mongodb_client_async.py
tencentcloud_sdk_python_mongodb-3.1.41.dist-info/METADATA
tencentcloud_sdk_python_mongodb-3.1.41.dist-info/WHEEL
tencentcloud_sdk_python_mongodb-3.1.41.dist-info/top_level.txt
tencentcloud_sdk_python_mongodb-3.1.41.dist-info/RECORD
